tests/__init__.py
tests/tests.py
vega_lite_linter/__init__.py
vega_lite_linter/lint.py
vega_lite_linter/data/airports.csv
vega_lite_linter/data/cars.json
vega_lite_linter/data/movies.json
vega_lite_linter/data/seattle-weather.csv
vega_lite_linter/data/weather.json
vega_lite_linter/dataParse/__init__.py
vega_lite_linter/dataParse/dataParse.py
vega_lite_linter/fixer/__init__.py
vega_lite_linter/fixer/action.py
vega_lite_linter/fixer/cost.py
vega_lite_linter/fixer/fixer.py
vega_lite_linter/fixer/rules.py
vega_lite_linter/fixer/actions/__init__.py
vega_lite_linter/fixer/actions/intro.py
vega_lite_linter/fixer/actions/router.py
vega_lite_linter/fixer/optimize/__init__.py
vega_lite_linter/fixer/optimize/optimize.py
vega_lite_linter/linter/__init__.py
vega_lite_linter/linter/linter.py
vega_lite_linter/linter/run_clingo.py
vega_lite_linter/linter/rules/__init__.py
vega_lite_linter/linter/rules/define.lp
vega_lite_linter/linter/rules/hard.lp
vega_lite_linter/linter/rules/hard_origin.lp
vega_lite_linter/linter/rules/intro copy.py
vega_lite_linter/linter/rules/intro.py
vega_lite_linter/linter/rules/output.lp
vega_lite_linter/translator/__init__.py
vega_lite_linter/translator/translator.py
vega_lite_linter-0.0.1.dist-info/LICENSE
vega_lite_linter-0.0.1.dist-info/METADATA
vega_lite_linter-0.0.1.dist-info/WHEEL
vega_lite_linter-0.0.1.dist-info/top_level.txt
vega_lite_linter-0.0.1.dist-info/RECORD
