Metadata-Version: 2.1
Name: vega-lite-linter
Version: 0.0.1
Summary: a python package for vega-lite lint and quick-fix
Home-page: https://github.com/idvxlab/vega-lite-linter
Author: idvxlab
Author-email: idvxlab@gmail.com
License: UNKNOWN
Platform: UNKNOWN
Classifier: Programming Language :: Python :: 3
Classifier: License :: OSI Approved :: MIT License
Classifier: Operating System :: OS Independent
Requires-Dist: clyngor (~=0.3.31)
Requires-Dist: PuLP (~=2.4)
Requires-Dist: pandas (~=1.2.3)
Requires-Dist: vega-datasets (~=0.7.0)
